MANIFEST.in
README.rst
setup.py
collective/__init__.py
collective.csv2atvocabularymanager.egg-info/PKG-INFO
collective.csv2atvocabularymanager.egg-info/SOURCES.txt
collective.csv2atvocabularymanager.egg-info/dependency_links.txt
collective.csv2atvocabularymanager.egg-info/entry_points.txt
collective.csv2atvocabularymanager.egg-info/namespace_packages.txt
collective.csv2atvocabularymanager.egg-info/not-zip-safe
collective.csv2atvocabularymanager.egg-info/requires.txt
collective.csv2atvocabularymanager.egg-info/top_level.txt
collective/csv2atvocabularymanager/__init__.py
collective/csv2atvocabularymanager/configure.zcml
collective/csv2atvocabularymanager/csv_import.py
collective/csv2atvocabularymanager/testing.py
collective/csv2atvocabularymanager/tests/__init__.py
collective/csv2atvocabularymanager/tests/test_linguaplone.py
collective/csv2atvocabularymanager/tests/test_utility.py
collective/csv2atvocabularymanager/tests/csv/example1.csv
collective/csv2atvocabularymanager/tests/csv/example2.csv
collective/csv2atvocabularymanager/tests/csv/example3.csv
collective/csv2atvocabularymanager/tests/csv/example4.csv
collective/csv2atvocabularymanager/tests/csv/example5.csv
collective/csv2atvocabularymanager/tests/csv/example6.csv
docs/HISTORY.txt
docs/INSTALL.txt
docs/LICENSE.GPL
docs/LICENSE.txt