Metadata-Version: 1.0
Name: collective.csv2atvocabularymanager
Version: 0.1.1
Summary: Plone utility for importing your ATVocabularyManager vocabularies from CSV sources (with LinguaPlone support)
Home-page: http://github.com/RedTurtle/collective.csv2atvocabularymanager
Author: RedTurtle Technology
Author-email: sviluppoplone@redturtle.it
License: GPL
Keywords: plone vocabulary atvocabularymanager archetypes
Platform: UNKNOWN
Classifier: Framework :: Plone
Classifier: Framework :: Plone :: 3.3
Classifier: Framework :: Plone :: 4.0
Classifier: Framework :: Plone :: 4.1
Classifier: Framework :: Plone :: 4.2
Classifier: Development Status :: 4 - Beta
Classifier: Programming Language :: Python
Classifier: Intended Audience :: Developers
